datasette_import_table/__init__.py
datasette_import_table/templates/datasette_import_table.html
datasette_import_table-0.3.dist-info/METADATA
datasette_import_table-0.3.dist-info/WHEEL
datasette_import_table-0.3.dist-info/entry_points.txt
datasette_import_table-0.3.dist-info/top_level.txt
datasette_import_table-0.3.dist-info/RECORD
