Metadata-Version: 2.1
Name: datasette-import-table
Version: 0.3
Summary: Datasette plugin for importing tables from other Datasette instances
Home-page: https://github.com/simonw/datasette-import-table
Author: Simon Willison
License: Apache License, Version 2.0
Project-URL: Issues, https://github.com/simonw/datasette-import-table/issues
Project-URL: CI, https://github.com/simonw/datasette-import-table/actions
Project-URL: Changelog, https://github.com/simonw/datasette-import-table/releases
Platform: UNKNOWN
Requires-Dist: datasette
Requires-Dist: httpx
Requires-Dist: sqlite-utils
Provides-Extra: test
Requires-Dist: pytest ; extra == 'test'
Requires-Dist: pytest-asyncio ; extra == 'test'
Requires-Dist: httpx ; extra == 'test'
Requires-Dist: pytest-httpx ; extra == 'test'
